asonethod/Automation1.py
asonethod/CreateAccount.py
asonethod/Friend.py
asonethod/GetInfo.py
asonethod/GetToken.py
asonethod/Login.py
asonethod/Privacy.py
asonethod/Setting.py
asonethod/Tools.py
asonethod/__init__.py
asonethod-0.0.2.dist-info/METADATA
asonethod-0.0.2.dist-info/WHEEL
asonethod-0.0.2.dist-info/top_level.txt
asonethod-0.0.2.dist-info/RECORD
