Metadata-Version: 2.1
Name: asonethod
Version: 0.0.2
Summary: Facebook Scrapper
Home-page: https://github.com/zaypaihtet/asonethod
Author: Crd Dapunta Khurayra X
Author-email: zaypaihtet@gmail.com
License: MIT
Keywords: facebook-scraper,facebook-parser,facebook-scraper-without-apikey,facebook-tools,facebook
Classifier: Development Status :: 3 - Alpha
Classifier: Intended Audience :: Developers
Classifier: Topic :: Software Development :: Build Tools
Classifier: License :: OSI Approved :: MIT License
Classifier: Natural Language :: English
Classifier: Programming Language :: Python :: 3.9
Classifier: Programming Language :: Python :: 3.10
Classifier: Programming Language :: Python :: 3.11
Classifier: Programming Language :: Python :: 3 :: Only
Requires-Python: >=3.9
Requires-Dist: requests
